{
  "rsn": "FoolinSlays",
  "updated": "2026-07-20T04:46:35.938941+00:00",
  "clues": {
    "Clue Scrolls (all)": {
      "count": 543,
      "rank": 43597
    },
    "Clue Scrolls (beginner)": {
      "count": 151,
      "rank": 19737
    },
    "Clue Scrolls (easy)": {
      "count": 51,
      "rank": 70266
    },
    "Clue Scrolls (medium)": {
      "count": 154,
      "rank": 43386
    },
    "Clue Scrolls (hard)": {
      "count": 148,
      "rank": 53809
    },
    "Clue Scrolls (elite)": {
      "count": 36,
      "rank": 39655
    },
    "Clue Scrolls (master)": {
      "count": 3,
      "rank": 61224
    }
  }
}