{
  "rsn": "FoolinSlays",
  "updated": "2026-07-17T16:40:24.006028+00:00",
  "clues": {
    "Clue Scrolls (all)": {
      "count": 543,
      "rank": 43531
    },
    "Clue Scrolls (beginner)": {
      "count": 151,
      "rank": 19697
    },
    "Clue Scrolls (easy)": {
      "count": 51,
      "rank": 70175
    },
    "Clue Scrolls (medium)": {
      "count": 154,
      "rank": 43333
    },
    "Clue Scrolls (hard)": {
      "count": 148,
      "rank": 53752
    },
    "Clue Scrolls (elite)": {
      "count": 36,
      "rank": 39607
    },
    "Clue Scrolls (master)": {
      "count": 3,
      "rank": 61177
    }
  }
}