{
  "rsn": "FoolinSlays",
  "updated": "2026-06-18T15:26:31.122082+00:00",
  "clues": {
    "Clue Scrolls (all)": {
      "count": 543,
      "rank": 42925
    },
    "Clue Scrolls (beginner)": {
      "count": 151,
      "rank": 19251
    },
    "Clue Scrolls (easy)": {
      "count": 51,
      "rank": 69363
    },
    "Clue Scrolls (medium)": {
      "count": 154,
      "rank": 42749
    },
    "Clue Scrolls (hard)": {
      "count": 148,
      "rank": 53205
    },
    "Clue Scrolls (elite)": {
      "count": 36,
      "rank": 39179
    },
    "Clue Scrolls (master)": {
      "count": 3,
      "rank": 60713
    }
  }
}