{
  "rsn": "FoolinSlays",
  "updated": "2026-07-08T14:09:47.207460+00:00",
  "clues": {
    "Clue Scrolls (all)": {
      "count": 543,
      "rank": 43339
    },
    "Clue Scrolls (beginner)": {
      "count": 151,
      "rank": 19562
    },
    "Clue Scrolls (easy)": {
      "count": 51,
      "rank": 69887
    },
    "Clue Scrolls (medium)": {
      "count": 154,
      "rank": 43143
    },
    "Clue Scrolls (hard)": {
      "count": 148,
      "rank": 53580
    },
    "Clue Scrolls (elite)": {
      "count": 36,
      "rank": 39471
    },
    "Clue Scrolls (master)": {
      "count": 3,
      "rank": 61029
    }
  }
}