{
  "rsn": "FoolinSlays",
  "updated": "2026-05-11T09:40:59.376107+00:00",
  "skills": {
    "Overall": {
      "level": 2212,
      "xp": 218439118,
      "rank": 41195,
      "progress": null
    },
    "Attack": {
      "level": 97,
      "xp": 10935438,
      "rank": 68747,
      "progress": {
        "progress": 21.8,
        "xp_to_level": 870168
      }
    },
    "Defence": {
      "level": 97,
      "xp": 11247259,
      "rank": 58088,
      "progress": {
        "progress": 49.8,
        "xp_to_level": 558347
      }
    },
    "Strength": {
      "level": 98,
      "xp": 11955365,
      "rank": 100370,
      "progress": {
        "progress": 12.2,
        "xp_to_level": 1079066
      }
    },
    "Hitpoints": {
      "level": 99,
      "xp": 23637699,
      "rank": 56807,
      "progress": {
        "progress": 100,
        "xp_to_level": 0
      }
    },
    "Ranged": {
      "level": 99,
      "xp": 19727539,
      "rank": 56150,
      "progress": {
        "progress": 100,
        "xp_to_level": 0
      }
    },
    "Prayer": {
      "level": 83,
      "xp": 2768200,
      "rank": 68984,
      "progress": {
        "progress": 34.2,
        "xp_to_level": 183173
      }
    },
    "Magic": {
      "level": 99,
      "xp": 15269843,
      "rank": 53791,
      "progress": {
        "progress": 100,
        "xp_to_level": 0
      }
    },
    "Cooking": {
      "level": 91,
      "xp": 6011419,
      "rank": 84616,
      "progress": {
        "progress": 17.7,
        "xp_to_level": 505834
      }
    },
    "Woodcutting": {
      "level": 92,
      "xp": 6560528,
      "rank": 66171,
      "progress": {
        "progress": 6.4,
        "xp_to_level": 635101
      }
    },
    "Fletching": {
      "level": 90,
      "xp": 5841511,
      "rank": 61793,
      "progress": {
        "progress": 89.0,
        "xp_to_level": 61320
      }
    },
    "Fishing": {
      "level": 85,
      "xp": 3440907,
      "rank": 114244,
      "progress": {
        "progress": 53.7,
        "xp_to_level": 156885
      }
    },
    "Firemaking": {
      "level": 95,
      "xp": 9565700,
      "rank": 166883,
      "progress": {
        "progress": 87.0,
        "xp_to_level": 118877
      }
    },
    "Crafting": {
      "level": 95,
      "xp": 8874190,
      "rank": 47880,
      "progress": {
        "progress": 11.2,
        "xp_to_level": 810387
      }
    },
    "Smithing": {
      "level": 84,
      "xp": 2992914,
      "rank": 85351,
      "progress": {
        "progress": 13.5,
        "xp_to_level": 265680
      }
    },
    "Mining": {
      "level": 97,
      "xp": 10957651,
      "rank": 43273,
      "progress": {
        "progress": 23.8,
        "xp_to_level": 847955
      }
    },
    "Herblore": {
      "level": 93,
      "xp": 7449912,
      "rank": 44813,
      "progress": {
        "progress": 34.0,
        "xp_to_level": 494702
      }
    },
    "Agility": {
      "level": 77,
      "xp": 1584592,
      "rank": 136907,
      "progress": {
        "progress": 71.0,
        "xp_to_level": 44608
      }
    },
    "Thieving": {
      "level": 88,
      "xp": 4797925,
      "rank": 95190,
      "progress": {
        "progress": 90.3,
        "xp_to_level": 44370
      }
    },
    "Slayer": {
      "level": 97,
      "xp": 10830656,
      "rank": 54528,
      "progress": {
        "progress": 12.4,
        "xp_to_level": 974950
      }
    },
    "Farming": {
      "level": 99,
      "xp": 19362084,
      "rank": 20430,
      "progress": {
        "progress": 100,
        "xp_to_level": 0
      }
    },
    "Runecraft": {
      "level": 85,
      "xp": 3381004,
      "rank": 59159,
      "progress": {
        "progress": 36.1,
        "xp_to_level": 216788
      }
    },
    "Hunter": {
      "level": 89,
      "xp": 5196968,
      "rank": 61685,
      "progress": {
        "progress": 70.4,
        "xp_to_level": 149364
      }
    },
    "Construction": {
      "level": 84,
      "xp": 2996045,
      "rank": 67128,
      "progress": {
        "progress": 14.5,
        "xp_to_level": 262549
      }
    },
    "Sailing": {
      "level": 99,
      "xp": 13053769,
      "rank": 9905,
      "progress": {
        "progress": 100,
        "xp_to_level": 0
      }
    }
  },
  "milestones": {
    "total_level": 2212,
    "total_xp": 218439118,
    "combat_level": 122.62,
    "skills_99": 5,
    "num_skills": 24
  }
}