{
  "rsn": "FoolinSlays",
  "updated": "2026-04-04T12:58:28.352208+00:00",
  "skills": {
    "Overall": {
      "level": 2192,
      "xp": 204560866,
      "rank": 45083,
      "progress": null
    },
    "Attack": {
      "level": 97,
      "xp": 10863024,
      "rank": 67753,
      "progress": {
        "progress": 15.3,
        "xp_to_level": 942582
      }
    },
    "Defence": {
      "level": 97,
      "xp": 10981685,
      "rank": 57799,
      "progress": {
        "progress": 26.0,
        "xp_to_level": 823921
      }
    },
    "Strength": {
      "level": 97,
      "xp": 11405195,
      "rank": 101944,
      "progress": {
        "progress": 64.0,
        "xp_to_level": 400411
      }
    },
    "Hitpoints": {
      "level": 99,
      "xp": 22792413,
      "rank": 58144,
      "progress": {
        "progress": 100,
        "xp_to_level": 0
      }
    },
    "Ranged": {
      "level": 99,
      "xp": 19114093,
      "rank": 56727,
      "progress": {
        "progress": 100,
        "xp_to_level": 0
      }
    },
    "Prayer": {
      "level": 83,
      "xp": 2733704,
      "rank": 68292,
      "progress": {
        "progress": 21.8,
        "xp_to_level": 217669
      }
    },
    "Magic": {
      "level": 99,
      "xp": 14615975,
      "rank": 56444,
      "progress": {
        "progress": 100,
        "xp_to_level": 0
      }
    },
    "Cooking": {
      "level": 91,
      "xp": 5980749,
      "rank": 83719,
      "progress": {
        "progress": 12.7,
        "xp_to_level": 536504
      }
    },
    "Woodcutting": {
      "level": 92,
      "xp": 6560078,
      "rank": 64970,
      "progress": {
        "progress": 6.3,
        "xp_to_level": 635551
      }
    },
    "Fletching": {
      "level": 84,
      "xp": 3172370,
      "rank": 93210,
      "progress": {
        "progress": 71.9,
        "xp_to_level": 86224
      }
    },
    "Fishing": {
      "level": 85,
      "xp": 3437757,
      "rank": 112985,
      "progress": {
        "progress": 52.8,
        "xp_to_level": 160035
      }
    },
    "Firemaking": {
      "level": 95,
      "xp": 9565200,
      "rank": 166096,
      "progress": {
        "progress": 86.9,
        "xp_to_level": 119377
      }
    },
    "Crafting": {
      "level": 94,
      "xp": 8167742,
      "rank": 52997,
      "progress": {
        "progress": 27.0,
        "xp_to_level": 603816
      }
    },
    "Smithing": {
      "level": 84,
      "xp": 2990504,
      "rank": 84121,
      "progress": {
        "progress": 12.7,
        "xp_to_level": 268090
      }
    },
    "Mining": {
      "level": 94,
      "xp": 8523225,
      "rank": 53711,
      "progress": {
        "progress": 70.0,
        "xp_to_level": 248333
      }
    },
    "Herblore": {
      "level": 93,
      "xp": 7449452,
      "rank": 44039,
      "progress": {
        "progress": 33.9,
        "xp_to_level": 495162
      }
    },
    "Agility": {
      "level": 77,
      "xp": 1494550,
      "rank": 142526,
      "progress": {
        "progress": 12.3,
        "xp_to_level": 134650
      }
    },
    "Thieving": {
      "level": 88,
      "xp": 4711820,
      "rank": 94840,
      "progress": {
        "progress": 71.4,
        "xp_to_level": 130475
      }
    },
    "Slayer": {
      "level": 96,
      "xp": 10226393,
      "rank": 57407,
      "progress": {
        "progress": 53.7,
        "xp_to_level": 466236
      }
    },
    "Farming": {
      "level": 99,
      "xp": 19288076,
      "rank": 20222,
      "progress": {
        "progress": 100,
        "xp_to_level": 0
      }
    },
    "Runecraft": {
      "level": 80,
      "xp": 1991951,
      "rank": 84388,
      "progress": {
        "progress": 2.8,
        "xp_to_level": 200867
      }
    },
    "Hunter": {
      "level": 89,
      "xp": 5177664,
      "rank": 60959,
      "progress": {
        "progress": 66.5,
        "xp_to_level": 168668
      }
    },
    "Construction": {
      "level": 84,
      "xp": 2995625,
      "rank": 65980,
      "progress": {
        "progress": 14.4,
        "xp_to_level": 262969
      }
    },
    "Sailing": {
      "level": 96,
      "xp": 10321621,
      "rank": 18506,
      "progress": {
        "progress": 63.2,
        "xp_to_level": 371008
      }
    }
  },
  "milestones": {
    "total_level": 2192,
    "total_xp": 204560866,
    "combat_level": 122.3,
    "skills_99": 4,
    "num_skills": 24
  }
}