{
  "rsn": "FoolinSlays",
  "updated": "2026-03-06T12:58:53.106632+00:00",
  "skills": {
    "Overall": {
      "level": 2176,
      "xp": 186947260,
      "rank": 47595,
      "progress": null
    },
    "Attack": {
      "level": 96,
      "xp": 9955904,
      "rank": 69823,
      "progress": {
        "progress": 26.9,
        "xp_to_level": 736725
      }
    },
    "Defence": {
      "level": 96,
      "xp": 9936059,
      "rank": 59786,
      "progress": {
        "progress": 24.9,
        "xp_to_level": 756570
      }
    },
    "Strength": {
      "level": 96,
      "xp": 10168416,
      "rank": 108676,
      "progress": {
        "progress": 48.0,
        "xp_to_level": 524213
      }
    },
    "Hitpoints": {
      "level": 99,
      "xp": 20408968,
      "rank": 63777,
      "progress": {
        "progress": 100,
        "xp_to_level": 0
      }
    },
    "Ranged": {
      "level": 99,
      "xp": 16483239,
      "rank": 62850,
      "progress": {
        "progress": 100,
        "xp_to_level": 0
      }
    },
    "Prayer": {
      "level": 83,
      "xp": 2701982,
      "rank": 67500,
      "progress": {
        "progress": 10.4,
        "xp_to_level": 249391
      }
    },
    "Magic": {
      "level": 99,
      "xp": 13655006,
      "rank": 61081,
      "progress": {
        "progress": 100,
        "xp_to_level": 0
      }
    },
    "Cooking": {
      "level": 91,
      "xp": 5915829,
      "rank": 83515,
      "progress": {
        "progress": 2.1,
        "xp_to_level": 601424
      }
    },
    "Woodcutting": {
      "level": 92,
      "xp": 6544358,
      "rank": 63867,
      "progress": {
        "progress": 4.0,
        "xp_to_level": 651271
      }
    },
    "Fletching": {
      "level": 80,
      "xp": 2127113,
      "rank": 116801,
      "progress": {
        "progress": 68.2,
        "xp_to_level": 65705
      }
    },
    "Fishing": {
      "level": 85,
      "xp": 3397347,
      "rank": 112812,
      "progress": {
        "progress": 40.9,
        "xp_to_level": 200445
      }
    },
    "Firemaking": {
      "level": 95,
      "xp": 9565200,
      "rank": 165357,
      "progress": {
        "progress": 86.9,
        "xp_to_level": 119377
      }
    },
    "Crafting": {
      "level": 93,
      "xp": 7543700,
      "rank": 62044,
      "progress": {
        "progress": 46.5,
        "xp_to_level": 400914
      }
    },
    "Smithing": {
      "level": 83,
      "xp": 2691293,
      "rank": 89928,
      "progress": {
        "progress": 6.5,
        "xp_to_level": 260080
      }
    },
    "Mining": {
      "level": 89,
      "xp": 4956512,
      "rank": 93461,
      "progress": {
        "progress": 22.7,
        "xp_to_level": 389820
      }
    },
    "Herblore": {
      "level": 93,
      "xp": 7389110,
      "rank": 43595,
      "progress": {
        "progress": 25.8,
        "xp_to_level": 555504
      }
    },
    "Agility": {
      "level": 76,
      "xp": 1354389,
      "rank": 155270,
      "progress": {
        "progress": 12.9,
        "xp_to_level": 121192
      }
    },
    "Thieving": {
      "level": 88,
      "xp": 4711820,
      "rank": 93798,
      "progress": {
        "progress": 71.4,
        "xp_to_level": 130475
      }
    },
    "Slayer": {
      "level": 95,
      "xp": 9112135,
      "rank": 64499,
      "progress": {
        "progress": 37.3,
        "xp_to_level": 572442
      }
    },
    "Farming": {
      "level": 99,
      "xp": 18180700,
      "rank": 23294,
      "progress": {
        "progress": 100,
        "xp_to_level": 0
      }
    },
    "Runecraft": {
      "level": 80,
      "xp": 1991951,
      "rank": 83005,
      "progress": {
        "progress": 2.8,
        "xp_to_level": 200867
      }
    },
    "Hunter": {
      "level": 89,
      "xp": 4892664,
      "rank": 63002,
      "progress": {
        "progress": 10.0,
        "xp_to_level": 453668
      }
    },
    "Construction": {
      "level": 84,
      "xp": 2988401,
      "rank": 65251,
      "progress": {
        "progress": 12.1,
        "xp_to_level": 270193
      }
    },
    "Sailing": {
      "level": 96,
      "xp": 10275164,
      "rank": 16903,
      "progress": {
        "progress": 58.6,
        "xp_to_level": 417465
      }
    }
  },
  "milestones": {
    "total_level": 2176,
    "total_xp": 186947260,
    "combat_level": 121.4,
    "skills_99": 4,
    "num_skills": 24
  }
}