{
  "rsn": "FoolinSlays",
  "updated": "2026-07-20T09:14:39.711641+00:00",
  "skills": {
    "Overall": {
      "level": 2246,
      "xp": 265676937,
      "rank": 35451,
      "progress": null
    },
    "Attack": {
      "level": 99,
      "xp": 13823517,
      "rank": 47997,
      "progress": {
        "progress": 100,
        "xp_to_level": 0
      }
    },
    "Defence": {
      "level": 99,
      "xp": 13236137,
      "rank": 49348,
      "progress": {
        "progress": 100,
        "xp_to_level": 0
      }
    },
    "Strength": {
      "level": 99,
      "xp": 14383445,
      "rank": 68095,
      "progress": {
        "progress": 100,
        "xp_to_level": 0
      }
    },
    "Hitpoints": {
      "level": 99,
      "xp": 30137382,
      "rank": 44418,
      "progress": {
        "progress": 100,
        "xp_to_level": 0
      }
    },
    "Ranged": {
      "level": 99,
      "xp": 30743531,
      "rank": 38552,
      "progress": {
        "progress": 100,
        "xp_to_level": 0
      }
    },
    "Prayer": {
      "level": 85,
      "xp": 3345464,
      "rank": 61479,
      "progress": {
        "progress": 25.6,
        "xp_to_level": 252328
      }
    },
    "Magic": {
      "level": 99,
      "xp": 16919445,
      "rank": 48216,
      "progress": {
        "progress": 100,
        "xp_to_level": 0
      }
    },
    "Cooking": {
      "level": 96,
      "xp": 9692365,
      "rank": 57646,
      "progress": {
        "progress": 0.8,
        "xp_to_level": 1000264
      }
    },
    "Woodcutting": {
      "level": 99,
      "xp": 13036643,
      "rank": 43635,
      "progress": {
        "progress": 100,
        "xp_to_level": 0
      }
    },
    "Fletching": {
      "level": 91,
      "xp": 6185435,
      "rank": 57327,
      "progress": {
        "progress": 46.0,
        "xp_to_level": 331818
      }
    },
    "Fishing": {
      "level": 88,
      "xp": 4826259,
      "rank": 90396,
      "progress": {
        "progress": 96.5,
        "xp_to_level": 16036
      }
    },
    "Firemaking": {
      "level": 96,
      "xp": 10165023,
      "rank": 166042,
      "progress": {
        "progress": 47.7,
        "xp_to_level": 527606
      }
    },
    "Crafting": {
      "level": 95,
      "xp": 9354074,
      "rank": 46626,
      "progress": {
        "progress": 63.8,
        "xp_to_level": 330503
      }
    },
    "Smithing": {
      "level": 86,
      "xp": 3620509,
      "rank": 74259,
      "progress": {
        "progress": 6.1,
        "xp_to_level": 351785
      }
    },
    "Mining": {
      "level": 98,
      "xp": 12937833,
      "rank": 40483,
      "progress": {
        "progress": 92.1,
        "xp_to_level": 96598
      }
    },
    "Herblore": {
      "level": 93,
      "xp": 7703288,
      "rank": 45317,
      "progress": {
        "progress": 67.8,
        "xp_to_level": 241326
      }
    },
    "Agility": {
      "level": 80,
      "xp": 2109921,
      "rank": 110094,
      "progress": {
        "progress": 59.9,
        "xp_to_level": 82897
      }
    },
    "Thieving": {
      "level": 89,
      "xp": 5046503,
      "rank": 95319,
      "progress": {
        "progress": 40.5,
        "xp_to_level": 299829
      }
    },
    "Slayer": {
      "level": 99,
      "xp": 13877075,
      "rank": 38503,
      "progress": {
        "progress": 100,
        "xp_to_level": 0
      }
    },
    "Farming": {
      "level": 99,
      "xp": 19557283,
      "rank": 20871,
      "progress": {
        "progress": 100,
        "xp_to_level": 0
      }
    },
    "Runecraft": {
      "level": 86,
      "xp": 3675239,
      "rank": 55328,
      "progress": {
        "progress": 20.7,
        "xp_to_level": 297055
      }
    },
    "Hunter": {
      "level": 89,
      "xp": 5230862,
      "rank": 63620,
      "progress": {
        "progress": 77.1,
        "xp_to_level": 115470
      }
    },
    "Construction": {
      "level": 84,
      "xp": 3000232,
      "rank": 69828,
      "progress": {
        "progress": 15.9,
        "xp_to_level": 258362
      }
    },
    "Sailing": {
      "level": 99,
      "xp": 13069472,
      "rank": 11786,
      "progress": {
        "progress": 100,
        "xp_to_level": 0
      }
    }
  },
  "milestones": {
    "total_level": 2246,
    "total_xp": 265676937,
    "combat_level": 124.35,
    "skills_99": 10,
    "num_skills": 24,
    "ca_points": null,
    "ca_rank": null,
    "collections_logged": 566,
    "collections_rank": 33632
  }
}