{
  "rsn": "FoolinSlays",
  "updated": "2026-03-04T02:07:27.401408+00:00",
  "skills": {
    "Overall": {
      "level": 2174,
      "xp": 185207371,
      "rank": 48015,
      "progress": null
    },
    "Attack": {
      "level": 96,
      "xp": 9846532,
      "rank": 70161,
      "progress": {
        "progress": 16.1,
        "xp_to_level": 846097
      }
    },
    "Defence": {
      "level": 96,
      "xp": 9777688,
      "rank": 60299,
      "progress": {
        "progress": 9.2,
        "xp_to_level": 914941
      }
    },
    "Strength": {
      "level": 96,
      "xp": 10016922,
      "rank": 109723,
      "progress": {
        "progress": 33.0,
        "xp_to_level": 675707
      }
    },
    "Hitpoints": {
      "level": 99,
      "xp": 20204472,
      "rank": 64327,
      "progress": {
        "progress": 100,
        "xp_to_level": 0
      }
    },
    "Ranged": {
      "level": 99,
      "xp": 16461427,
      "rank": 62824,
      "progress": {
        "progress": 100,
        "xp_to_level": 0
      }
    },
    "Prayer": {
      "level": 83,
      "xp": 2684127,
      "rank": 67843,
      "progress": {
        "progress": 4.0,
        "xp_to_level": 267246
      }
    },
    "Magic": {
      "level": 99,
      "xp": 13516696,
      "rank": 61982,
      "progress": {
        "progress": 100,
        "xp_to_level": 0
      }
    },
    "Cooking": {
      "level": 91,
      "xp": 5913309,
      "rank": 83472,
      "progress": {
        "progress": 1.7,
        "xp_to_level": 603944
      }
    },
    "Woodcutting": {
      "level": 92,
      "xp": 6542648,
      "rank": 63789,
      "progress": {
        "progress": 3.7,
        "xp_to_level": 652981
      }
    },
    "Fletching": {
      "level": 80,
      "xp": 2127113,
      "rank": 116641,
      "progress": {
        "progress": 68.2,
        "xp_to_level": 65705
      }
    },
    "Fishing": {
      "level": 85,
      "xp": 3395797,
      "rank": 112734,
      "progress": {
        "progress": 40.4,
        "xp_to_level": 201995
      }
    },
    "Firemaking": {
      "level": 95,
      "xp": 9565200,
      "rank": 165349,
      "progress": {
        "progress": 86.9,
        "xp_to_level": 119377
      }
    },
    "Crafting": {
      "level": 93,
      "xp": 7541735,
      "rank": 61999,
      "progress": {
        "progress": 46.2,
        "xp_to_level": 402879
      }
    },
    "Smithing": {
      "level": 83,
      "xp": 2690208,
      "rank": 89841,
      "progress": {
        "progress": 6.1,
        "xp_to_level": 261165
      }
    },
    "Mining": {
      "level": 88,
      "xp": 4509533,
      "rank": 97919,
      "progress": {
        "progress": 27.1,
        "xp_to_level": 332762
      }
    },
    "Herblore": {
      "level": 93,
      "xp": 7388900,
      "rank": 43545,
      "progress": {
        "progress": 25.8,
        "xp_to_level": 555714
      }
    },
    "Agility": {
      "level": 76,
      "xp": 1354259,
      "rank": 155150,
      "progress": {
        "progress": 12.8,
        "xp_to_level": 121322
      }
    },
    "Thieving": {
      "level": 88,
      "xp": 4711820,
      "rank": 93719,
      "progress": {
        "progress": 71.4,
        "xp_to_level": 130475
      }
    },
    "Slayer": {
      "level": 95,
      "xp": 8975202,
      "rank": 65512,
      "progress": {
        "progress": 22.3,
        "xp_to_level": 709375
      }
    },
    "Farming": {
      "level": 99,
      "xp": 18112624,
      "rank": 23478,
      "progress": {
        "progress": 100,
        "xp_to_level": 0
      }
    },
    "Runecraft": {
      "level": 80,
      "xp": 1991551,
      "rank": 82977,
      "progress": {
        "progress": 2.7,
        "xp_to_level": 201267
      }
    },
    "Hunter": {
      "level": 88,
      "xp": 4616043,
      "rank": 65755,
      "progress": {
        "progress": 50.4,
        "xp_to_level": 226252
      }
    },
    "Construction": {
      "level": 84,
      "xp": 2988401,
      "rank": 65155,
      "progress": {
        "progress": 12.1,
        "xp_to_level": 270193
      }
    },
    "Sailing": {
      "level": 96,
      "xp": 10275164,
      "rank": 16761,
      "progress": {
        "progress": 58.6,
        "xp_to_level": 417465
      }
    }
  },
  "milestones": {
    "total_level": 2174,
    "total_xp": 185207371,
    "combat_level": 121.4,
    "skills_99": 4,
    "num_skills": 24
  }
}