{
  "rsn": "FoolinSlays",
  "updated": "2026-05-14T14:14:36.104222+00:00",
  "skills": {
    "Overall": {
      "level": 2216,
      "xp": 221032472,
      "rank": 40253,
      "progress": null
    },
    "Attack": {
      "level": 97,
      "xp": 10935577,
      "rank": 68856,
      "progress": {
        "progress": 21.8,
        "xp_to_level": 870029
      }
    },
    "Defence": {
      "level": 97,
      "xp": 11247397,
      "rank": 58163,
      "progress": {
        "progress": 49.8,
        "xp_to_level": 558209
      }
    },
    "Strength": {
      "level": 98,
      "xp": 12707960,
      "rank": 96004,
      "progress": {
        "progress": 73.4,
        "xp_to_level": 326471
      }
    },
    "Hitpoints": {
      "level": 99,
      "xp": 23899871,
      "rank": 56201,
      "progress": {
        "progress": 100,
        "xp_to_level": 0
      }
    },
    "Ranged": {
      "level": 99,
      "xp": 19762119,
      "rank": 56135,
      "progress": {
        "progress": 100,
        "xp_to_level": 0
      }
    },
    "Prayer": {
      "level": 83,
      "xp": 2768643,
      "rank": 69076,
      "progress": {
        "progress": 34.3,
        "xp_to_level": 182730
      }
    },
    "Magic": {
      "level": 99,
      "xp": 15293611,
      "rank": 53767,
      "progress": {
        "progress": 100,
        "xp_to_level": 0
      }
    },
    "Cooking": {
      "level": 91,
      "xp": 6011634,
      "rank": 84720,
      "progress": {
        "progress": 17.7,
        "xp_to_level": 505619
      }
    },
    "Woodcutting": {
      "level": 92,
      "xp": 6560528,
      "rank": 66281,
      "progress": {
        "progress": 6.4,
        "xp_to_level": 635101
      }
    },
    "Fletching": {
      "level": 91,
      "xp": 6170009,
      "rank": 55314,
      "progress": {
        "progress": 43.5,
        "xp_to_level": 347244
      }
    },
    "Fishing": {
      "level": 85,
      "xp": 3501469,
      "rank": 112658,
      "progress": {
        "progress": 71.6,
        "xp_to_level": 96323
      }
    },
    "Firemaking": {
      "level": 95,
      "xp": 9565700,
      "rank": 166951,
      "progress": {
        "progress": 87.0,
        "xp_to_level": 118877
      }
    },
    "Crafting": {
      "level": 95,
      "xp": 8983472,
      "rank": 47152,
      "progress": {
        "progress": 23.2,
        "xp_to_level": 701105
      }
    },
    "Smithing": {
      "level": 84,
      "xp": 2992914,
      "rank": 85466,
      "progress": {
        "progress": 13.5,
        "xp_to_level": 265680
      }
    },
    "Mining": {
      "level": 97,
      "xp": 11316742,
      "rank": 42341,
      "progress": {
        "progress": 56.1,
        "xp_to_level": 488864
      }
    },
    "Herblore": {
      "level": 93,
      "xp": 7469075,
      "rank": 44732,
      "progress": {
        "progress": 36.5,
        "xp_to_level": 475539
      }
    },
    "Agility": {
      "level": 78,
      "xp": 1650410,
      "rank": 132626,
      "progress": {
        "progress": 12.5,
        "xp_to_level": 148398
      }
    },
    "Thieving": {
      "level": 89,
      "xp": 4842441,
      "rank": 94989,
      "progress": {
        "progress": 0.0,
        "xp_to_level": 503891
      }
    },
    "Slayer": {
      "level": 97,
      "xp": 11051815,
      "rank": 53317,
      "progress": {
        "progress": 32.3,
        "xp_to_level": 753791
      }
    },
    "Farming": {
      "level": 99,
      "xp": 19362084,
      "rank": 20463,
      "progress": {
        "progress": 100,
        "xp_to_level": 0
      }
    },
    "Runecraft": {
      "level": 86,
      "xp": 3674839,
      "rank": 53276,
      "progress": {
        "progress": 20.6,
        "xp_to_level": 297455
      }
    },
    "Hunter": {
      "level": 89,
      "xp": 5214348,
      "rank": 61631,
      "progress": {
        "progress": 73.8,
        "xp_to_level": 131984
      }
    },
    "Construction": {
      "level": 84,
      "xp": 2996045,
      "rank": 67216,
      "progress": {
        "progress": 14.5,
        "xp_to_level": 262549
      }
    },
    "Sailing": {
      "level": 99,
      "xp": 13053769,
      "rank": 9952,
      "progress": {
        "progress": 100,
        "xp_to_level": 0
      }
    }
  },
  "milestones": {
    "total_level": 2216,
    "total_xp": 221032472,
    "combat_level": 122.62,
    "skills_99": 5,
    "num_skills": 24
  }
}