{
  "rsn": "GIM Foolin",
  "updated": "2026-07-20T03:43:31.672368+00:00",
  "skills": {
    "Overall": {
      "level": 1149,
      "xp": 15358061,
      "rank": -1,
      "progress": null
    },
    "Attack": {
      "level": 77,
      "xp": 1571217,
      "rank": 1512038,
      "progress": {
        "progress": 62.3,
        "xp_to_level": 57983
      }
    },
    "Defence": {
      "level": 77,
      "xp": 1571218,
      "rank": 1377574,
      "progress": {
        "progress": 62.3,
        "xp_to_level": 57982
      }
    },
    "Strength": {
      "level": 77,
      "xp": 1571213,
      "rank": 1957290,
      "progress": {
        "progress": 62.3,
        "xp_to_level": 57987
      }
    },
    "Hitpoints": {
      "level": 79,
      "xp": 1913369,
      "rank": 1876396,
      "progress": {
        "progress": 61.2,
        "xp_to_level": 72699
      }
    },
    "Ranged": {
      "level": 71,
      "xp": 819751,
      "rank": -1,
      "progress": {
        "progress": 6.3,
        "xp_to_level": 79506
      }
    },
    "Prayer": {
      "level": 31,
      "xp": 15452,
      "rank": -1,
      "progress": {
        "progress": 38.1,
        "xp_to_level": 1004
      }
    },
    "Magic": {
      "level": 70,
      "xp": 737801,
      "rank": -1,
      "progress": {
        "progress": 0.2,
        "xp_to_level": 76644
      }
    },
    "Cooking": {
      "level": 48,
      "xp": 86853,
      "rank": -1,
      "progress": {
        "progress": 44.1,
        "xp_to_level": 4868
      }
    },
    "Woodcutting": {
      "level": 75,
      "xp": 1226528,
      "rank": 1196459,
      "progress": {
        "progress": 12.8,
        "xp_to_level": 109915
      }
    },
    "Fletching": {
      "level": 49,
      "xp": 99894,
      "rank": -1,
      "progress": {
        "progress": 85.0,
        "xp_to_level": 1439
      }
    },
    "Fishing": {
      "level": 53,
      "xp": 139445,
      "rank": -1,
      "progress": {
        "progress": 20.0,
        "xp_to_level": 11427
      }
    },
    "Firemaking": {
      "level": 82,
      "xp": 2462218,
      "rank": 978330,
      "progress": {
        "progress": 16.3,
        "xp_to_level": 210896
      }
    },
    "Crafting": {
      "level": 46,
      "xp": 71456,
      "rank": -1,
      "progress": {
        "progress": 48.6,
        "xp_to_level": 3671
      }
    },
    "Smithing": {
      "level": 33,
      "xp": 19802,
      "rank": -1,
      "progress": {
        "progress": 78.7,
        "xp_to_level": 422
      }
    },
    "Mining": {
      "level": 80,
      "xp": 2002638,
      "rank": 797557,
      "progress": {
        "progress": 8.0,
        "xp_to_level": 190180
      }
    },
    "Herblore": {
      "level": 3,
      "xp": 250,
      "rank": -1,
      "progress": {
        "progress": 74.5,
        "xp_to_level": 26
      }
    },
    "Agility": {
      "level": 30,
      "xp": 14168,
      "rank": -1,
      "progress": {
        "progress": 54.8,
        "xp_to_level": 665
      }
    },
    "Thieving": {
      "level": 29,
      "xp": 12313,
      "rank": -1,
      "progress": {
        "progress": 21.2,
        "xp_to_level": 1050
      }
    },
    "Slayer": {
      "level": 20,
      "xp": 4555,
      "rank": -1,
      "progress": {
        "progress": 15.5,
        "xp_to_level": 463
      }
    },
    "Farming": {
      "level": 1,
      "xp": 46,
      "rank": -1,
      "progress": {
        "progress": 55.4,
        "xp_to_level": 37
      }
    },
    "Runecraft": {
      "level": 1,
      "xp": 0,
      "rank": -1,
      "progress": {
        "progress": 0.0,
        "xp_to_level": 83
      }
    },
    "Hunter": {
      "level": 9,
      "xp": 1043,
      "rank": -1,
      "progress": {
        "progress": 40.0,
        "xp_to_level": 111
      }
    },
    "Construction": {
      "level": 35,
      "xp": 22466,
      "rank": -1,
      "progress": {
        "progress": 2.5,
        "xp_to_level": 2349
      }
    },
    "Sailing": {
      "level": 73,
      "xp": 994365,
      "rank": 265533,
      "progress": {
        "progress": 1.4,
        "xp_to_level": 101913
      }
    }
  },
  "milestones": {
    "total_level": 1149,
    "total_xp": 15358061,
    "combat_level": 92.8,
    "skills_99": 0,
    "num_skills": 24,
    "ca_points": null,
    "ca_rank": null,
    "collections_logged": 26,
    "collections_rank": -1
  }
}