{
  "rsn": "GIM Foolin",
  "updated": "2026-07-24T02:05:17.349542+00:00",
  "skills": {
    "Overall": {
      "level": 1289,
      "xp": 16169943,
      "rank": 1962908,
      "progress": null
    },
    "Attack": {
      "level": 78,
      "xp": 1713973,
      "rank": 1482975,
      "progress": {
        "progress": 50.0,
        "xp_to_level": 84835
      }
    },
    "Defence": {
      "level": 78,
      "xp": 1687747,
      "rank": 1354604,
      "progress": {
        "progress": 34.5,
        "xp_to_level": 111061
      }
    },
    "Strength": {
      "level": 78,
      "xp": 1701517,
      "rank": 1922731,
      "progress": {
        "progress": 42.6,
        "xp_to_level": 97291
      }
    },
    "Hitpoints": {
      "level": 80,
      "xp": 2028224,
      "rank": 1841002,
      "progress": {
        "progress": 20.4,
        "xp_to_level": 164594
      }
    },
    "Ranged": {
      "level": 71,
      "xp": 822526,
      "rank": -1,
      "progress": {
        "progress": 9.5,
        "xp_to_level": 76731
      }
    },
    "Prayer": {
      "level": 32,
      "xp": 16578,
      "rank": -1,
      "progress": {
        "progress": 6.8,
        "xp_to_level": 1669
      }
    },
    "Magic": {
      "level": 70,
      "xp": 753059,
      "rank": -1,
      "progress": {
        "progress": 20.1,
        "xp_to_level": 61386
      }
    },
    "Cooking": {
      "level": 48,
      "xp": 88928,
      "rank": -1,
      "progress": {
        "progress": 67.9,
        "xp_to_level": 2793
      }
    },
    "Woodcutting": {
      "level": 75,
      "xp": 1231984,
      "rank": 1193073,
      "progress": {
        "progress": 17.1,
        "xp_to_level": 104459
      }
    },
    "Fletching": {
      "level": 50,
      "xp": 102300,
      "rank": -1,
      "progress": {
        "progress": 9.1,
        "xp_to_level": 9645
      }
    },
    "Fishing": {
      "level": 56,
      "xp": 197525,
      "rank": -1,
      "progress": {
        "progress": 70.2,
        "xp_to_level": 5729
      }
    },
    "Firemaking": {
      "level": 82,
      "xp": 2462278,
      "rank": 979264,
      "progress": {
        "progress": 16.3,
        "xp_to_level": 210836
      }
    },
    "Crafting": {
      "level": 48,
      "xp": 91103,
      "rank": -1,
      "progress": {
        "progress": 92.9,
        "xp_to_level": 618
      }
    },
    "Smithing": {
      "level": 36,
      "xp": 24844,
      "rank": -1,
      "progress": {
        "progress": 1.1,
        "xp_to_level": 2629
      }
    },
    "Mining": {
      "level": 80,
      "xp": 2024638,
      "rank": 789807,
      "progress": {
        "progress": 18.7,
        "xp_to_level": 168180
      }
    },
    "Herblore": {
      "level": 34,
      "xp": 22130,
      "rank": -1,
      "progress": {
        "progress": 87.4,
        "xp_to_level": 276
      }
    },
    "Agility": {
      "level": 41,
      "xp": 43281,
      "rank": -1,
      "progress": {
        "progress": 48.4,
        "xp_to_level": 2248
      }
    },
    "Thieving": {
      "level": 47,
      "xp": 78904,
      "rank": -1,
      "progress": {
        "progress": 47.9,
        "xp_to_level": 4110
      }
    },
    "Slayer": {
      "level": 20,
      "xp": 4671,
      "rank": -1,
      "progress": {
        "progress": 36.7,
        "xp_to_level": 347
      }
    },
    "Farming": {
      "level": 41,
      "xp": 44135,
      "rank": 1981186,
      "progress": {
        "progress": 68.0,
        "xp_to_level": 1394
      }
    },
    "Runecraft": {
      "level": 27,
      "xp": 10149,
      "rank": -1,
      "progress": {
        "progress": 38.3,
        "xp_to_level": 675
      }
    },
    "Hunter": {
      "level": 9,
      "xp": 1043,
      "rank": -1,
      "progress": {
        "progress": 40.0,
        "xp_to_level": 111
      }
    },
    "Construction": {
      "level": 35,
      "xp": 24041,
      "rank": -1,
      "progress": {
        "progress": 67.9,
        "xp_to_level": 774
      }
    },
    "Sailing": {
      "level": 73,
      "xp": 994365,
      "rank": 267063,
      "progress": {
        "progress": 1.4,
        "xp_to_level": 101913
      }
    }
  },
  "milestones": {
    "total_level": 1289,
    "total_xp": 16169943,
    "combat_level": 94.2,
    "skills_99": 0,
    "num_skills": 24,
    "ca_points": null,
    "ca_rank": null,
    "collections_logged": 34,
    "collections_rank": -1
  }
}