{
  "rsn": "FoolinSlays",
  "updated": "2026-04-14T07:48:28.774641+00:00",
  "bosses": {
    "Rifts closed": {
      "kc": 225,
      "rank": 55219
    },
    "Abyssal Sire": {
      "kc": 246,
      "rank": 42027
    },
    "Alchemical Hydra": {
      "kc": 209,
      "rank": 50136
    },
    "Amoxliatl": {
      "kc": 62,
      "rank": 25359
    },
    "Araxxor": {
      "kc": 486,
      "rank": 27539
    },
    "Barrows Chests": {
      "kc": 353,
      "rank": 78853
    },
    "Brutus": {
      "kc": 45,
      "rank": 56396
    },
    "Bryophyta": {
      "kc": 5,
      "rank": 68917
    },
    "Calvar'ion": {
      "kc": 59,
      "rank": 55724
    },
    "Cerberus": {
      "kc": 474,
      "rank": 44341
    },
    "Chaos Elemental": {
      "kc": 1,
      "rank": -1
    },
    "Chaos Fanatic": {
      "kc": 11,
      "rank": 58531
    },
    "Crazy Archaeologist": {
      "kc": 26,
      "rank": 101422
    },
    "Dagannoth Prime": {
      "kc": 3,
      "rank": -1
    },
    "Dagannoth Rex": {
      "kc": 34,
      "rank": 156690
    },
    "Dagannoth Supreme": {
      "kc": 2,
      "rank": -1
    },
    "Deranged Archaeologist": {
      "kc": 25,
      "rank": 77876
    },
    "Duke Sucellus": {
      "kc": 4,
      "rank": -1
    },
    "Giant Mole": {
      "kc": 25,
      "rank": 69688
    },
    "Grotesque Guardians": {
      "kc": 25,
      "rank": 53132
    },
    "Hespori": {
      "kc": 123,
      "rank": 22593
    },
    "Kalphite Queen": {
      "kc": 1,
      "rank": -1
    },
    "King Black Dragon": {
      "kc": 26,
      "rank": 60059
    },
    "Kraken": {
      "kc": 2118,
      "rank": 18618
    },
    "K'ril Tsutsaroth": {
      "kc": 3,
      "rank": -1
    },
    "Lunar Chests": {
      "kc": 414,
      "rank": 8092
    },
    "Mimic": {
      "kc": 1,
      "rank": 52362
    },
    "Obor": {
      "kc": 5,
      "rank": 76642
    },
    "Phantom Muspah": {
      "kc": 1,
      "rank": -1
    },
    "Sarachnis": {
      "kc": 47,
      "rank": 48441
    },
    "Scorpia": {
      "kc": 1,
      "rank": -1
    },
    "Scurrius": {
      "kc": 54,
      "rank": 36747
    },
    "Shellbane Gryphon": {
      "kc": 576,
      "rank": 2581
    },
    "Skotizo": {
      "kc": 26,
      "rank": 49566
    },
    "Tempoross": {
      "kc": 25,
      "rank": 219116
    },
    "The Gauntlet": {
      "kc": 20,
      "rank": 48496
    },
    "The Corrupted Gauntlet": {
      "kc": 961,
      "rank": 6464
    },
    "The Hueycoatl": {
      "kc": 185,
      "rank": 14195
    },
    "The Leviathan": {
      "kc": 1,
      "rank": -1
    },
    "The Royal Titans": {
      "kc": 496,
      "rank": 9774
    },
    "The Whisperer": {
      "kc": 1,
      "rank": -1
    },
    "Thermonuclear Smoke Devil": {
      "kc": 1,
      "rank": -1
    },
    "TzTok-Jad": {
      "kc": 1,
      "rank": -1
    },
    "Vardorvis": {
      "kc": 1,
      "rank": -1
    },
    "Vorkath": {
      "kc": 6,
      "rank": 100065
    },
    "Wintertodt": {
      "kc": 460,
      "rank": 139110
    },
    "Zulrah": {
      "kc": 26,
      "rank": 95363
    }
  }
}