{
  "rsn": "FoolinSlays",
  "updated": "2026-05-13T03:32:48.788276+00:00",
  "bosses": {
    "Rifts closed": {
      "kc": 416,
      "rank": 18246
    },
    "Abyssal Sire": {
      "kc": 246,
      "rank": 42531
    },
    "Alchemical Hydra": {
      "kc": 209,
      "rank": 50587
    },
    "Amoxliatl": {
      "kc": 62,
      "rank": 25872
    },
    "Araxxor": {
      "kc": 556,
      "rank": 24738
    },
    "Barrows Chests": {
      "kc": 353,
      "rank": 79287
    },
    "Brutus": {
      "kc": 45,
      "rank": 59967
    },
    "Bryophyta": {
      "kc": 5,
      "rank": 69263
    },
    "Calvar'ion": {
      "kc": 59,
      "rank": 56738
    },
    "Cerberus": {
      "kc": 474,
      "rank": 44805
    },
    "Chaos Elemental": {
      "kc": 1,
      "rank": -1
    },
    "Chaos Fanatic": {
      "kc": 11,
      "rank": 59115
    },
    "Crazy Archaeologist": {
      "kc": 26,
      "rank": 102111
    },
    "Dagannoth Prime": {
      "kc": 3,
      "rank": -1
    },
    "Dagannoth Rex": {
      "kc": 34,
      "rank": 158132
    },
    "Dagannoth Supreme": {
      "kc": 2,
      "rank": -1
    },
    "Deranged Archaeologist": {
      "kc": 25,
      "rank": 78542
    },
    "Duke Sucellus": {
      "kc": 4,
      "rank": -1
    },
    "Giant Mole": {
      "kc": 25,
      "rank": 70075
    },
    "Grotesque Guardians": {
      "kc": 25,
      "rank": 53684
    },
    "Hespori": {
      "kc": 123,
      "rank": 22848
    },
    "Kalphite Queen": {
      "kc": 1,
      "rank": -1
    },
    "King Black Dragon": {
      "kc": 26,
      "rank": 60441
    },
    "Kraken": {
      "kc": 2509,
      "rank": 14072
    },
    "K'ril Tsutsaroth": {
      "kc": 3,
      "rank": -1
    },
    "Lunar Chests": {
      "kc": 414,
      "rank": 8310
    },
    "Mimic": {
      "kc": 1,
      "rank": 52488
    },
    "Obor": {
      "kc": 5,
      "rank": 77039
    },
    "Phantom Muspah": {
      "kc": 1,
      "rank": -1
    },
    "Sarachnis": {
      "kc": 47,
      "rank": 49153
    },
    "Scorpia": {
      "kc": 1,
      "rank": -1
    },
    "Scurrius": {
      "kc": 54,
      "rank": 37111
    },
    "Shellbane Gryphon": {
      "kc": 576,
      "rank": 2751
    },
    "Skotizo": {
      "kc": 26,
      "rank": 49778
    },
    "Tempoross": {
      "kc": 25,
      "rank": 221325
    },
    "The Gauntlet": {
      "kc": 20,
      "rank": 48765
    },
    "The Corrupted Gauntlet": {
      "kc": 965,
      "rank": 6462
    },
    "The Hueycoatl": {
      "kc": 185,
      "rank": 14447
    },
    "The Leviathan": {
      "kc": 1,
      "rank": -1
    },
    "The Royal Titans": {
      "kc": 496,
      "rank": 9989
    },
    "The Whisperer": {
      "kc": 1,
      "rank": -1
    },
    "Thermonuclear Smoke Devil": {
      "kc": 1,
      "rank": -1
    },
    "TzTok-Jad": {
      "kc": 1,
      "rank": -1
    },
    "Vardorvis": {
      "kc": 1,
      "rank": -1
    },
    "Vorkath": {
      "kc": 6,
      "rank": 100952
    },
    "Wintertodt": {
      "kc": 460,
      "rank": 139519
    },
    "Zulrah": {
      "kc": 26,
      "rank": 96159
    }
  }
}