{
  "rsn": "FoolinSlays",
  "updated": "2026-01-27T17:40:39.513534+00:00",
  "clues": {
    "Clue Scrolls (all)": {
      "count": 438,
      "rank": 50392
    },
    "Clue Scrolls (beginner)": {
      "count": 146,
      "rank": 17080
    },
    "Clue Scrolls (easy)": {
      "count": 48,
      "rank": 67998
    },
    "Clue Scrolls (medium)": {
      "count": 73,
      "rank": 74387
    },
    "Clue Scrolls (hard)": {
      "count": 138,
      "rank": 54720
    },
    "Clue Scrolls (elite)": {
      "count": 32,
      "rank": 40272
    },
    "Clue Scrolls (master)": {
      "count": 1,
      "rank": 86933
    }
  }
}