{
  "rsn": "FoolinSlays",
  "updated": "2026-01-22T06:37:13.217863+00:00",
  "clues": {
    "Clue Scrolls (all)": {
      "count": 427,
      "rank": 51579
    },
    "Clue Scrolls (beginner)": {
      "count": 146,
      "rank": 16954
    },
    "Clue Scrolls (easy)": {
      "count": 48,
      "rank": 67789
    },
    "Clue Scrolls (medium)": {
      "count": 62,
      "rank": 82575
    },
    "Clue Scrolls (hard)": {
      "count": 138,
      "rank": 54592
    },
    "Clue Scrolls (elite)": {
      "count": 32,
      "rank": 40183
    },
    "Clue Scrolls (master)": {
      "count": 1,
      "rank": 86875
    }
  }
}