{
  "rsn": "FoolinSlays",
  "updated": "2026-04-21T02:42:10.131280+00:00",
  "clues": {
    "Clue Scrolls (all)": {
      "count": 543,
      "rank": 41923
    },
    "Clue Scrolls (beginner)": {
      "count": 151,
      "rank": 18454
    },
    "Clue Scrolls (easy)": {
      "count": 51,
      "rank": 68049
    },
    "Clue Scrolls (medium)": {
      "count": 154,
      "rank": 41859
    },
    "Clue Scrolls (hard)": {
      "count": 148,
      "rank": 52430
    },
    "Clue Scrolls (elite)": {
      "count": 36,
      "rank": 38580
    },
    "Clue Scrolls (master)": {
      "count": 3,
      "rank": 60122
    }
  }
}