{
  "rsn": "FoolinSlays",
  "updated": "2026-05-17T03:05:41.542795+00:00",
  "clues": {
    "Clue Scrolls (all)": {
      "count": 543,
      "rank": 42305
    },
    "Clue Scrolls (beginner)": {
      "count": 151,
      "rank": 18760
    },
    "Clue Scrolls (easy)": {
      "count": 51,
      "rank": 68516
    },
    "Clue Scrolls (medium)": {
      "count": 154,
      "rank": 42205
    },
    "Clue Scrolls (hard)": {
      "count": 148,
      "rank": 52708
    },
    "Clue Scrolls (elite)": {
      "count": 36,
      "rank": 38784
    },
    "Clue Scrolls (master)": {
      "count": 3,
      "rank": 60348
    }
  }
}