{
  "rsn": "FoolinSlays",
  "updated": "2026-02-06T02:10:15.537145+00:00",
  "skills": {
    "Overall": {
      "level": 2142,
      "xp": 168653871,
      "rank": 54795,
      "progress": null
    },
    "Attack": {
      "level": 95,
      "xp": 9476809,
      "rank": 70385,
      "progress": {
        "progress": 77.2,
        "xp_to_level": 207768
      }
    },
    "Defence": {
      "level": 95,
      "xp": 8783693,
      "rank": 63601,
      "progress": {
        "progress": 1.3,
        "xp_to_level": 900884
      }
    },
    "Strength": {
      "level": 96,
      "xp": 9710475,
      "rank": 110329,
      "progress": {
        "progress": 2.6,
        "xp_to_level": 982154
      }
    },
    "Hitpoints": {
      "level": 99,
      "xp": 18448075,
      "rank": 68874,
      "progress": {
        "progress": 100,
        "xp_to_level": 0
      }
    },
    "Ranged": {
      "level": 99,
      "xp": 13718012,
      "rank": 72063,
      "progress": {
        "progress": 100,
        "xp_to_level": 0
      }
    },
    "Prayer": {
      "level": 82,
      "xp": 2604438,
      "rank": 67676,
      "progress": {
        "progress": 72.8,
        "xp_to_level": 68676
      }
    },
    "Magic": {
      "level": 98,
      "xp": 12423313,
      "rank": 67776,
      "progress": {
        "progress": 50.3,
        "xp_to_level": 611118
      }
    },
    "Cooking": {
      "level": 86,
      "xp": 3808731,
      "rank": 110359,
      "progress": {
        "progress": 56.3,
        "xp_to_level": 163563
      }
    },
    "Woodcutting": {
      "level": 91,
      "xp": 6257758,
      "rank": 64952,
      "progress": {
        "progress": 57.8,
        "xp_to_level": 259495
      }
    },
    "Fletching": {
      "level": 80,
      "xp": 2124793,
      "rank": 114833,
      "progress": {
        "progress": 67.1,
        "xp_to_level": 68025
      }
    },
    "Fishing": {
      "level": 83,
      "xp": 2700623,
      "rank": 137426,
      "progress": {
        "progress": 9.9,
        "xp_to_level": 250750
      }
    },
    "Firemaking": {
      "level": 95,
      "xp": 9565200,
      "rank": 164799,
      "progress": {
        "progress": 86.9,
        "xp_to_level": 119377
      }
    },
    "Crafting": {
      "level": 93,
      "xp": 7302248,
      "rank": 68585,
      "progress": {
        "progress": 14.2,
        "xp_to_level": 642366
      }
    },
    "Smithing": {
      "level": 78,
      "xp": 1680449,
      "rank": 112072,
      "progress": {
        "progress": 30.2,
        "xp_to_level": 118359
      }
    },
    "Mining": {
      "level": 84,
      "xp": 3174173,
      "rank": 123217,
      "progress": {
        "progress": 72.5,
        "xp_to_level": 84421
      }
    },
    "Herblore": {
      "level": 93,
      "xp": 7230279,
      "rank": 44187,
      "progress": {
        "progress": 4.6,
        "xp_to_level": 714335
      }
    },
    "Agility": {
      "level": 73,
      "xp": 1073492,
      "rank": 187819,
      "progress": {
        "progress": 78.0,
        "xp_to_level": 22786
      }
    },
    "Thieving": {
      "level": 88,
      "xp": 4664033,
      "rank": 93257,
      "progress": {
        "progress": 61.0,
        "xp_to_level": 178262
      }
    },
    "Slayer": {
      "level": 94,
      "xp": 8607781,
      "rank": 67025,
      "progress": {
        "progress": 80.2,
        "xp_to_level": 163777
      }
    },
    "Farming": {
      "level": 99,
      "xp": 17175720,
      "rank": 26670,
      "progress": {
        "progress": 100,
        "xp_to_level": 0
      }
    },
    "Runecraft": {
      "level": 75,
      "xp": 1225300,
      "rank": 112524,
      "progress": {
        "progress": 11.8,
        "xp_to_level": 111143
      }
    },
    "Hunter": {
      "level": 86,
      "xp": 3873557,
      "rank": 75130,
      "progress": {
        "progress": 73.6,
        "xp_to_level": 98737
      }
    },
    "Construction": {
      "level": 84,
      "xp": 2985616,
      "rank": 64222,
      "progress": {
        "progress": 11.1,
        "xp_to_level": 272978
      }
    },
    "Sailing": {
      "level": 96,
      "xp": 10039303,
      "rank": 15163,
      "progress": {
        "progress": 35.2,
        "xp_to_level": 653326
      }
    }
  },
  "milestones": {
    "total_level": 2142,
    "total_xp": 168653871,
    "combat_level": 120.83,
    "skills_99": 3,
    "num_skills": 24
  }
}