{
  "rsn": "FoolinSlays",
  "updated": "2026-01-28T18:44:03.654408+00:00",
  "skills": {
    "Overall": {
      "level": 2133,
      "xp": 161606785,
      "rank": 56727,
      "progress": null
    },
    "Attack": {
      "level": 95,
      "xp": 8775389,
      "rank": 73955,
      "progress": {
        "progress": 0.4,
        "xp_to_level": 909188
      }
    },
    "Defence": {
      "level": 94,
      "xp": 8527305,
      "rank": 64346,
      "progress": {
        "progress": 70.5,
        "xp_to_level": 244253
      }
    },
    "Strength": {
      "level": 95,
      "xp": 8903565,
      "rank": 116514,
      "progress": {
        "progress": 14.5,
        "xp_to_level": 781012
      }
    },
    "Hitpoints": {
      "level": 99,
      "xp": 17772691,
      "rank": 70800,
      "progress": {
        "progress": 100,
        "xp_to_level": 0
      }
    },
    "Ranged": {
      "level": 99,
      "xp": 13667746,
      "rank": 71871,
      "progress": {
        "progress": 100,
        "xp_to_level": 0
      }
    },
    "Prayer": {
      "level": 82,
      "xp": 2587345,
      "rank": 67522,
      "progress": {
        "progress": 66.0,
        "xp_to_level": 85769
      }
    },
    "Magic": {
      "level": 98,
      "xp": 12201543,
      "rank": 68572,
      "progress": {
        "progress": 32.2,
        "xp_to_level": 832888
      }
    },
    "Cooking": {
      "level": 85,
      "xp": 3433258,
      "rank": 117542,
      "progress": {
        "progress": 51.5,
        "xp_to_level": 164534
      }
    },
    "Woodcutting": {
      "level": 90,
      "xp": 5580789,
      "rank": 71854,
      "progress": {
        "progress": 42.1,
        "xp_to_level": 322042
      }
    },
    "Fletching": {
      "level": 80,
      "xp": 2124793,
      "rank": 114279,
      "progress": {
        "progress": 67.1,
        "xp_to_level": 68025
      }
    },
    "Fishing": {
      "level": 82,
      "xp": 2664235,
      "rank": 139198,
      "progress": {
        "progress": 96.5,
        "xp_to_level": 8879
      }
    },
    "Firemaking": {
      "level": 95,
      "xp": 9565200,
      "rank": 164900,
      "progress": {
        "progress": 86.9,
        "xp_to_level": 119377
      }
    },
    "Crafting": {
      "level": 93,
      "xp": 7284607,
      "rank": 69030,
      "progress": {
        "progress": 11.9,
        "xp_to_level": 660007
      }
    },
    "Smithing": {
      "level": 78,
      "xp": 1675684,
      "rank": 111795,
      "progress": {
        "progress": 27.4,
        "xp_to_level": 123124
      }
    },
    "Mining": {
      "level": 83,
      "xp": 2882436,
      "rank": 128766,
      "progress": {
        "progress": 75.2,
        "xp_to_level": 68937
      }
    },
    "Herblore": {
      "level": 91,
      "xp": 5942119,
      "rank": 54205,
      "progress": {
        "progress": 6.4,
        "xp_to_level": 575134
      }
    },
    "Agility": {
      "level": 73,
      "xp": 1057852,
      "rank": 189460,
      "progress": {
        "progress": 62.8,
        "xp_to_level": 38426
      }
    },
    "Thieving": {
      "level": 88,
      "xp": 4663543,
      "rank": 93047,
      "progress": {
        "progress": 60.8,
        "xp_to_level": 178752
      }
    },
    "Slayer": {
      "level": 94,
      "xp": 8153793,
      "rank": 69672,
      "progress": {
        "progress": 25.3,
        "xp_to_level": 617765
      }
    },
    "Farming": {
      "level": 99,
      "xp": 16715766,
      "rank": 28542,
      "progress": {
        "progress": 100,
        "xp_to_level": 0
      }
    },
    "Runecraft": {
      "level": 75,
      "xp": 1225300,
      "rank": 112230,
      "progress": {
        "progress": 11.8,
        "xp_to_level": 111143
      }
    },
    "Hunter": {
      "level": 85,
      "xp": 3265241,
      "rank": 88819,
      "progress": {
        "progress": 2.0,
        "xp_to_level": 332551
      }
    },
    "Construction": {
      "level": 84,
      "xp": 2985216,
      "rank": 63935,
      "progress": {
        "progress": 11.0,
        "xp_to_level": 273378
      }
    },
    "Sailing": {
      "level": 96,
      "xp": 9951369,
      "rank": 14577,
      "progress": {
        "progress": 26.5,
        "xp_to_level": 741260
      }
    }
  },
  "milestones": {
    "total_level": 2133,
    "total_xp": 161606785,
    "combat_level": 120.25,
    "skills_99": 3,
    "num_skills": 24
  }
}