{
  "rsn": "FoolinSlays",
  "updated": "2026-02-17T18:59:02.317919+00:00",
  "skills": {
    "Overall": {
      "level": 2156,
      "xp": 176947153,
      "rank": 51802,
      "progress": null
    },
    "Attack": {
      "level": 96,
      "xp": 9707758,
      "rank": 70009,
      "progress": {
        "progress": 2.3,
        "xp_to_level": 984871
      }
    },
    "Defence": {
      "level": 95,
      "xp": 9295147,
      "rank": 61324,
      "progress": {
        "progress": 57.3,
        "xp_to_level": 389430
      }
    },
    "Strength": {
      "level": 96,
      "xp": 9841572,
      "rank": 110007,
      "progress": {
        "progress": 15.6,
        "xp_to_level": 851057
      }
    },
    "Hitpoints": {
      "level": 99,
      "xp": 19483757,
      "rank": 65913,
      "progress": {
        "progress": 100,
        "xp_to_level": 0
      }
    },
    "Ranged": {
      "level": 99,
      "xp": 15621859,
      "rank": 64832,
      "progress": {
        "progress": 100,
        "xp_to_level": 0
      }
    },
    "Prayer": {
      "level": 82,
      "xp": 2661712,
      "rank": 67477,
      "progress": {
        "progress": 95.5,
        "xp_to_level": 11402
      }
    },
    "Magic": {
      "level": 98,
      "xp": 12882200,
      "rank": 66147,
      "progress": {
        "progress": 87.6,
        "xp_to_level": 152231
      }
    },
    "Cooking": {
      "level": 88,
      "xp": 4573446,
      "rank": 99785,
      "progress": {
        "progress": 41.1,
        "xp_to_level": 268849
      }
    },
    "Woodcutting": {
      "level": 91,
      "xp": 6371423,
      "rank": 64553,
      "progress": {
        "progress": 76.3,
        "xp_to_level": 145830
      }
    },
    "Fletching": {
      "level": 80,
      "xp": 2127113,
      "rank": 115609,
      "progress": {
        "progress": 68.2,
        "xp_to_level": 65705
      }
    },
    "Fishing": {
      "level": 84,
      "xp": 2987420,
      "rank": 126189,
      "progress": {
        "progress": 11.7,
        "xp_to_level": 271174
      }
    },
    "Firemaking": {
      "level": 95,
      "xp": 9565200,
      "rank": 164993,
      "progress": {
        "progress": 86.9,
        "xp_to_level": 119377
      }
    },
    "Crafting": {
      "level": 93,
      "xp": 7489342,
      "rank": 62721,
      "progress": {
        "progress": 39.2,
        "xp_to_level": 455272
      }
    },
    "Smithing": {
      "level": 80,
      "xp": 2021602,
      "rank": 101920,
      "progress": {
        "progress": 17.2,
        "xp_to_level": 171216
      }
    },
    "Mining": {
      "level": 85,
      "xp": 3579309,
      "rank": 111888,
      "progress": {
        "progress": 94.6,
        "xp_to_level": 18483
      }
    },
    "Herblore": {
      "level": 93,
      "xp": 7297099,
      "rank": 43832,
      "progress": {
        "progress": 13.5,
        "xp_to_level": 647515
      }
    },
    "Agility": {
      "level": 75,
      "xp": 1230098,
      "rank": 168702,
      "progress": {
        "progress": 15.6,
        "xp_to_level": 106345
      }
    },
    "Thieving": {
      "level": 88,
      "xp": 4678201,
      "rank": 93504,
      "progress": {
        "progress": 64.1,
        "xp_to_level": 164094
      }
    },
    "Slayer": {
      "level": 95,
      "xp": 8802542,
      "rank": 66328,
      "progress": {
        "progress": 3.4,
        "xp_to_level": 882035
      }
    },
    "Farming": {
      "level": 99,
      "xp": 17800170,
      "rank": 24348,
      "progress": {
        "progress": 100,
        "xp_to_level": 0
      }
    },
    "Runecraft": {
      "level": 78,
      "xp": 1635922,
      "rank": 94522,
      "progress": {
        "progress": 4.0,
        "xp_to_level": 162886
      }
    },
    "Hunter": {
      "level": 87,
      "xp": 4032269,
      "rank": 72981,
      "progress": {
        "progress": 14.5,
        "xp_to_level": 353507
      }
    },
    "Construction": {
      "level": 84,
      "xp": 2986866,
      "rank": 64644,
      "progress": {
        "progress": 11.6,
        "xp_to_level": 271728
      }
    },
    "Sailing": {
      "level": 96,
      "xp": 10275126,
      "rank": 15773,
      "progress": {
        "progress": 58.6,
        "xp_to_level": 417503
      }
    }
  },
  "milestones": {
    "total_level": 2156,
    "total_xp": 176947153,
    "combat_level": 121.15,
    "skills_99": 3,
    "num_skills": 24
  }
}